fagflag/__init__.py
fagflag/__main__.py
fagflag/generator.py
fagflag-1.0.10.dist-info/LICENSE
fagflag-1.0.10.dist-info/METADATA
fagflag-1.0.10.dist-info/WHEEL
fagflag-1.0.10.dist-info/entry_points.txt
fagflag-1.0.10.dist-info/top_level.txt
fagflag-1.0.10.dist-info/RECORD
