Metadata-Version: 2.1
Name: fagflag
Version: 1.0.10
Summary: Generate pride flags as bitmap or vector images
Home-page: https://github.com/Red-Panda-Studios/fagflag
Author: disuko
Author-email: disuko@redpandastudios.net
License: MIT
Classifier: Programming Language :: Python :: 3
Classifier: License :: OSI Approved :: MIT License
Classifier: Operating System :: OS Independent
Requires-Python: >=3.6
License-File: LICENSE
Requires-Dist: Pillow
